open_code_interpreter/__init__.py
open_code_interpreter/interpreter.py
open_code_interpreter/configs/claude-2.1.config
open_code_interpreter/configs/claude-2.config
open_code_interpreter/configs/claude-3-opus.config
open_code_interpreter/configs/claude-3-sonnet.config
open_code_interpreter/configs/code-llama-phind.config
open_code_interpreter/configs/code-llama.config
open_code_interpreter/configs/gemini-pro.config
open_code_interpreter/configs/gpt-3.5-turbo.config
open_code_interpreter/configs/gpt-4.config
open_code_interpreter/configs/groq-llama2.config
open_code_interpreter/configs/groq-mixtral.config
open_code_interpreter/configs/local-model.config
open_code_interpreter/configs/mistral-7b.config
open_code_interpreter/configs/palm-2.config
open_code_interpreter/configs/star-chat.config
open_code_interpreter/configs/wizard-coder.config
open_code_interpreter/history/history.json
open_code_interpreter/libs/code_interpreter.py
open_code_interpreter/libs/gemini_vision.py
open_code_interpreter/libs/history_manager.py
open_code_interpreter/libs/interpreter_lib.py
open_code_interpreter/libs/logger.py
open_code_interpreter/libs/markdown_code.py
open_code_interpreter/libs/package_manager.py
open_code_interpreter/libs/utility_manager.py
open_code_interpreter/output/test.py
open_code_interpreter/system/system_message.txt
tests/__init__.py
tests/test_interpreter.py
open_code_interpreter-2.1.dist-info/LICENSE.txt
open_code_interpreter-2.1.dist-info/METADATA
open_code_interpreter-2.1.dist-info/WHEEL
open_code_interpreter-2.1.dist-info/entry_points.txt
open_code_interpreter-2.1.dist-info/top_level.txt
open_code_interpreter-2.1.dist-info/RECORD
