Metadata-Version: 2.1
Name: open-code-interpreter
Version: 2.1
Summary: An innovative open-source Code Interpreter with (GPT,Gemini,PALM,LLaMa) models.
Home-page: https://github.com/haseeb-heaven/open-code-interpreter
Author: Haseeb Mir
Author-email: haseebmir.hm@gmail.com
Classifier: Programming Language :: Python :: 3
Classifier: License :: OSI Approved :: MIT License
Classifier: Operating System :: OS Independent
Requires-Python: >=3.6
License-File: LICENSE.txt
